atomicwrites/__init__.py
atomicwrites-1.2.0.dist-info/METADATA
atomicwrites-1.2.0.dist-info/RECORD
atomicwrites-1.2.0.dist-info/WHEEL
atomicwrites-1.2.0.dist-info/top_level.txt
