Metadata-Version: 1.2
Name: atomicwrites
Version: 1.2.0
Summary: Atomic file writes.
Home-page: https://github.com/untitaker/python-atomicwrites
Author: Markus Unterwaditzer
Author-email: markus@unterwaditzer.net
License: MIT
Platform: UNKNOWN
Classifier: License :: OSI Approved :: MIT License
Classifier: Programming Language :: Python :: 2
Classifier: Programming Language :: Python :: 2.7
Classifier: Programming Language :: Python :: 3
Classifier: Programming Language :: Python :: 3.4
Classifier: Programming Language :: Python :: 3.5
Classifier: Programming Language :: Python :: 3.6
Classifier: Programming Language :: Python :: Implementation :: CPython
Requires-Python: >=2.7, !=3.0.*, !=3.1.*, !=3.2.*, !=3.3.*
